uconra/__init__.py
uconra/email_message.py
uconra/error.py
uconra/j_wt.py
uconra/login.py
uconra/register.py
uconra/smtp_mail.py
uconra/top_code.py
uconra-1.0.4.dist-info/LICENSE.txt
uconra-1.0.4.dist-info/METADATA
uconra-1.0.4.dist-info/WHEEL
uconra-1.0.4.dist-info/top_level.txt
uconra-1.0.4.dist-info/RECORD
