Metadata-Version: 2.1
Name: uconra
Version: 1.0.4
Summary: Application security authenticater
Author-email: motchello <motchello@gmail.com>
License: MIT License
Project-URL: Homepage, https://github.com/Uconra/uconra
Project-URL: Issues, https://github.com/Uconra/uconra/issues
Keywords: security,password,hashing,applications
Classifier: License :: OSI Approved :: MIT License
Classifier: Programming Language :: Python
Classifier: Programming Language :: Python :: 3
Classifier: Operating System :: MacOS :: MacOS X
Classifier: Operating System :: Microsoft :: Windows
Classifier: Intended Audience :: Developers
Requires-Python: >=3.11
License-File: LICENSE.txt
Requires-Dist: argon2-cffi>=23.1.0
Requires-Dist: argon2-cffi-bindings>=21.2.0
Requires-Dist: certifi>=2024.8.30
Requires-Dist: cffi>=1.17.1
Requires-Dist: charset-normalizer>=3.3.2
Requires-Dist: dnspython>=2.6.1
Requires-Dist: idna>=3.10
Requires-Dist: pycparser>=2.22
Requires-Dist: PyJWT>=2.9.0
Requires-Dist: requests>=2.32.3
Requires-Dist: urllib3>=2.2.3
